automation_lib/__init__.py
automation_lib/config_base.py
automation_lib/config_constants.py
automation_lib/config_utils.py
automation_lib/gmail/__init__.py
automation_lib/gmail/gmail_auth.py
automation_lib/gmail/gmail_helpers.py
automation_lib/gmail/gmail_runner.py
automation_lib/gmail/cli/__init__.py
automation_lib/gmail/cli/generate_token.py
automation_lib/gmail/cli/run_gmail.py
automation_lib/gmail/config/__init__.py
automation_lib/gmail/config/gmail_config.py
automation_lib/gmail/examples/__init__.py
automation_lib/gmail/examples/minimal_usage.py
automation_lib/gmail/schemas/__init__.py
automation_lib/gmail/schemas/gmail_schemas.py
automation_lib/gmail/tests/__init__.py
automation_lib/gmail/tests/integration/__init__.py
automation_lib/gmail/tests/integration/test_gmail_integration.py
automation_lib/gmail/tests/unit/__init__.py
automation_lib/gmail/tests/unit/test_gmail_helpers.py
automation_lib/gmail/tests/unit/test_gmail_runner.py
automation_lib/gmail/tests/unit/test_gmail_schemas.py
automation_lib/llm_prompt/__init__.py
automation_lib/llm_prompt/exceptions.py
automation_lib/llm_prompt/llm_prompt_helpers.py
automation_lib/llm_prompt/llm_prompt_runner.py
automation_lib/llm_prompt/model_resolver.py
automation_lib/llm_prompt/models.py
automation_lib/llm_prompt/cli/__init__.py
automation_lib/llm_prompt/cli/run_llm_prompt.py
automation_lib/llm_prompt/config/__init__.py
automation_lib/llm_prompt/config/llm_model_config.py
automation_lib/llm_prompt/config/llm_prompt_config.py
automation_lib/llm_prompt/examples/__init__.py
automation_lib/llm_prompt/examples/detailed_response_example.py
automation_lib/llm_prompt/examples/minimal_usage.py
automation_lib/llm_prompt/examples/structured_output_example.py
automation_lib/llm_prompt/examples/system_prompt_example.py
automation_lib/llm_prompt/examples/vision_example.py
automation_lib/llm_prompt/llm_providers/__init__.py
automation_lib/llm_prompt/llm_providers/base_provider.py
automation_lib-0.3.4.dist-info/licenses/LICENSE
automation_lib-0.3.4.dist-info/METADATA
automation_lib-0.3.4.dist-info/WHEEL
automation_lib-0.3.4.dist-info/top_level.txt
automation_lib-0.3.4.dist-info/RECORD
