Metadata-Version: 2.4
Name: automation-lib
Version: 0.3.4
Summary: A modular automation library with LLM integration, transcription, Gmail, and storage capabilities.
Author-email: Jakob Wowy <jakob.wowy@wooow-innovations.com>
Maintainer: Wooow Innovations UG
License: LGPL-3.0-or-later
Project-URL: Homepage, https://github.com/jakobwowy/automation_lib
Project-URL: Repository, https://github.com/jakobwowy/automation_lib
Project-URL: Issues, https://github.com/jakobwowy/automation_lib/issues
Project-URL: Documentation, https://github.com/jakobwowy/automation_lib#readme
Keywords: automation,llm,openai,gemini,transcription,gmail,supabase
Classifier: Development Status :: 4 - Beta
Classifier: Intended Audience :: Developers
Classifier: License :: OSI Approved :: GNU Lesser General Public License v3 or later (LGPLv3+)
Classifier: Programming Language :: Python :: 3
Classifier: Programming Language :: Python :: 3.12
Classifier: Operating System :: OS Independent
Classifier: Topic :: Software Development :: Libraries :: Python Modules
Classifier: Topic :: Communications :: Email
Classifier: Topic :: Multimedia :: Sound/Audio :: Speech
Requires-Python: >=3.12
License-File: LICENSE
Requires-Dist: prefect~=3.4.5
Requires-Dist: pydub~=0.25.1
Requires-Dist: python-dotenv~=1.1.0
Requires-Dist: pydantic[email]~=2.11.5
Requires-Dist: pydantic-settings~=2.9.1
Requires-Dist: google-cloud-speech~=2.32.0
Requires-Dist: supabase~=2.10.0
Requires-Dist: google-api-python-client~=2.130.0
Requires-Dist: google-auth-oauthlib~=1.2.0
Requires-Dist: google-auth-httplib2~=0.2.0
Requires-Dist: openai~=1.58.1
Requires-Dist: tabulate>=0.9.0
Requires-Dist: google-genai>=1.2.0
Requires-Dist: pypdf~=4.0.0
Requires-Dist: pytest>=8.4.1
Dynamic: license-file
